optimization/__init__.py
optimization/hyper.py
supervised_learning/__init__.py
supervised_learning/regression.py
supervised_learning/utils.py
supervised_learning/models/__init__.py
supervised_learning/models/wavenet.py
unsupervised_learning/__init__.py
unsupervised_learning/clustering/__init__.py
unsupervised_learning/clustering/_best_k.py
unsupervised_learning/clustering/_clustering.py
unsupervised_learning/clustering/_evaluation.py
ml_leoxiang66-0.8.0.dist-info/LICENSE
ml_leoxiang66-0.8.0.dist-info/METADATA
ml_leoxiang66-0.8.0.dist-info/WHEEL
ml_leoxiang66-0.8.0.dist-info/top_level.txt
ml_leoxiang66-0.8.0.dist-info/RECORD
